LICENCE
MANIFEST.in
README.md
setup.py
speedcord/__init__.py
speedcord/client.py
speedcord/client.pyi
speedcord/dispatcher.py
speedcord/dispatcher.pyi
speedcord/exceptions.py
speedcord/exceptions.pyi
speedcord/http.py
speedcord/http.pyi
speedcord/ratelimiter.py
speedcord/shard.py
speedcord/shard.pyi
speedcord/values.py
speedcord.egg-info/PKG-INFO
speedcord.egg-info/SOURCES.txt
speedcord.egg-info/dependency_links.txt
speedcord.egg-info/requires.txt
speedcord.egg-info/top_level.txt
speedcord/ext/__init__.py
speedcord/ext/typing/__init__.py
speedcord/ext/typing/context.py
speedcord/ext/typing/context.pyi