Metadata-Version: 2.1
Name: speedcord
Version: 0.3.123
Summary: A simple lightweight Discord library
Home-page: https://github.com/tag-epic/speedcord
Author: Epic
License: MIT
Platform: UNKNOWN
Requires-Python: >=3.8
